odte/Odte.py
odte/__init__.py
odte/_version.py
odte/tests/Odte_tests.py
odte/tests/__init__.py
odte/tests/utils.py
odte-1.0.0.post1.dist-info/METADATA
odte-1.0.0.post1.dist-info/WHEEL
odte-1.0.0.post1.dist-info/licenses/LICENSE
odte-1.0.0.post1.dist-info/RECORD
